pathwalker.py
pathwalker-1.1.1.dist-info/LICENSE.md
pathwalker-1.1.1.dist-info/METADATA
pathwalker-1.1.1.dist-info/WHEEL
pathwalker-1.1.1.dist-info/top_level.txt
pathwalker-1.1.1.dist-info/RECORD
