Metadata-Version: 2.1
Name: pathwalker
Version: 1.1.1
Summary: Helper functions to walk through file paths using pathlib.
Home-page: https://https://gitlab.com/david.scheliga/pathwalker
Author: David Scheliga
License: GNU General Public License V3 (GPLv3)
Project-URL: Documentation, https://pathwalker.readthedocs.io/en/latest/
Project-URL: Source Code Repository, https://https://gitlab.com/david.scheliga/pathwalker
Keywords: helper,filesystem,walk
Platform: UNKNOWN
Classifier: Development Status :: 5 - Production/Stable
Classifier: License :: OSI Approved :: GNU General Public License v3 (GPLv3)
Classifier: Operating System :: OS Independent
Classifier: Programming Language :: Python :: 3
Classifier: Programming Language :: Python :: 3.6
Classifier: Programming Language :: Python :: 3.7
Classifier: Programming Language :: Python :: 3.8
Classifier: Programming Language :: Python :: 3.9
Requires-Python: >=3.6
